biathlonresults/__init__.py
biathlonresults/api.py
biathlonresults/consts.py
biathlonresults-0.1.dist-info/LICENSE
biathlonresults-0.1.dist-info/METADATA
biathlonresults-0.1.dist-info/WHEEL
biathlonresults-0.1.dist-info/top_level.txt
biathlonresults-0.1.dist-info/RECORD
