Metadata-Version: 2.1
Name: biathlonresults
Version: 0.1
Summary: Python API wrapper for biathlonresults.com
Author-email: Ilya Porotikov <ip.tspl@gmail.com>
License: MIT License
Project-URL: Homepage, https://github.com/prtkv/biathlonresults
Keywords: biathlon,api,sport,ibu
License-File: LICENSE
Requires-Dist: requests>=2.22.0
